omnis/__init__.py
omnis/application/__init__.py
omnis/application/application.py
omnis/application/image_processing/__init__.py
omnis/application/image_processing/deblur/__init__.py
omnis/application/image_processing/deblur/deblur.py
omnis/application/image_processing/image_classification/__init__.py
omnis/application/image_processing/image_classification/image_classification.py
omnis/application/image_processing/image_classification/multi_label_image_classificataion.py
omnis/application/image_processing/image_segmentation/__init__.py
omnis/application/image_processing/image_segmentation/image_segmentation.py
omnis/application/image_processing/object_detection/__init__.py
omnis/application/image_processing/object_detection/object_detection.py
omnis/application/image_processing/style_transfer/__init__.py
omnis/application/image_processing/style_transfer/style_transfer.py
omnis/application/image_processing/style_transfer/style_transfer_worker.py
omnis/application/nlp/__init__.py
omnis/application/nlp/sentiment_analysis.py
omnis/application/nlp/text_generation.py
omnis/lib/__init__.py
omnis/lib/config_lib.py
omnis/lib/custom_callback.py
omnis/lib/general_lib.py
omnis/lib/generators.py
omnis/lib/image_lib.py
omnis/lib/layers_lib.py
omnis/lib/loss_lib.py
omnis/lib/model_lib.py
omnis/lib/saving_lib.py
omnis/lib/text_lib.py
omnis/lib/mask_rcnn/__init__.py
omnis/lib/mask_rcnn/config.py
omnis/lib/mask_rcnn/model.py
omnis/lib/mask_rcnn/parallel_model.py
omnis/lib/mask_rcnn/utils.py
omnis/lib/mask_rcnn/visualize.py
omnis/lib/yolo_v3/__init__.py
omnis/lib/yolo_v3/model.py
omnis/lib/yolo_v3/utils.py
Omnis-0.0.10.34.dist-info/LICENSE
Omnis-0.0.10.34.dist-info/METADATA
Omnis-0.0.10.34.dist-info/WHEEL
Omnis-0.0.10.34.dist-info/top_level.txt
Omnis-0.0.10.34.dist-info/RECORD
