Metadata-Version: 2.1
Name: Omnis
Version: 0.0.10.34
Summary: Deep Learning for everyone
Home-page: https://github.com/omnis-labs-company/omnis
Author: Omnis Labs Company
Author-email: mkh48v@snu.ac.kr
License: UNKNOWN
Platform: UNKNOWN
Classifier: Intended Audience :: Developers
Classifier: Intended Audience :: Education
Classifier: Intended Audience :: Science/Research
Classifier: Programming Language :: Python :: 3
Classifier: Programming Language :: Python :: 3.6
Classifier: License :: OSI Approved :: MIT License
Classifier: Operating System :: OS Independent
Requires-Dist: opencv-python (>=3.4.2.17)
Requires-Dist: tensorflow (>=1.12.0)
Requires-Dist: keras (>=2.2.4)
Requires-Dist: numpy (>=1.14.3)
Requires-Dist: scikit-image (>=0.13.1)
Requires-Dist: pandas (>=0.24.2)
